harbormaster/harbormaster.py
harbormaster-0.3.2.data/scripts/harbormaster
harbormaster-0.3.2.dist-info/METADATA
harbormaster-0.3.2.dist-info/WHEEL
harbormaster-0.3.2.dist-info/top_level.txt
harbormaster-0.3.2.dist-info/RECORD
