Metadata-Version: 2.1
Name: harbormaster
Version: 0.3.2
Summary: automating docker remote host forwarding
Home-page: https://github.com/tanishq-dubey/harbormaster
Author: Tanishq Dubey
Author-email: tanishq@dubey.dev
License: MIT
Platform: UNKNOWN
Classifier: Development Status :: 4 - Beta
Classifier: Intended Audience :: Developers
Classifier: Topic :: Software Development :: Build Tools
Classifier: Topic :: Utilities
Classifier: Environment :: Console
Classifier: License :: OSI Approved :: MIT License
Classifier: Programming Language :: Python :: 3
Requires-Dist: docker
